autodrome/__init__.py
autodrome/__main__.py
autodrome/envs/__init__.py
autodrome/envs/ats.py
autodrome/envs/env.py
autodrome/envs/ets2.py
autodrome/policeman/__init__.py
autodrome/policeman/definition.py
autodrome/policeman/map.py
autodrome/policeman/policeman.py
autodrome/simulator/__init__.py
autodrome/simulator/ats.py
autodrome/simulator/ets2.py
autodrome/simulator/simulator.py
autodrome/simulator/controller/__init__.py
autodrome/simulator/controller/controller.py
autodrome/simulator/controller/darwin.py
autodrome/simulator/telemetry/__init__.py
autodrome/simulator/telemetry/telemetry.py
autodrome/simulator/window/__init__.py
autodrome/simulator/window/darwin.py
autodrome/simulator/window/window.py
autodrome-0.1.0.dist-info/METADATA
autodrome-0.1.0.dist-info/WHEEL
autodrome-0.1.0.dist-info/top_level.txt
autodrome-0.1.0.dist-info/RECORD
